esse3_student/__init__.py
esse3_student/__main__.py
esse3_student/cli.py
esse3_student/esse3_wrapper.py
esse3_student/primitives.py
esse3_student/tui/__init__.py
esse3_student/tui/booklet.py
esse3_student/tui/exams.py
esse3_student/tui/main.py
esse3_student/tui/reservations.py
esse3_student/tui/style.css
esse3_student/tui/taxes.py
esse3_student/utils/__init__.py
esse3_student/utils/console.py
esse3_student/utils/primitives.py
esse3_student/utils/validators.py
esse3_student-3.7.0.dist-info/LICENSE
esse3_student-3.7.0.dist-info/METADATA
esse3_student-3.7.0.dist-info/WHEEL
esse3_student-3.7.0.dist-info/RECORD
