Metadata-Version: 2.1
Name: esse3-student
Version: 3.7.0
Summary: Esse3 command line utility
Author: Antonio Pallaria
Author-email: pallaria98@gmail.com
Requires-Python: >=3.9,<4.0
Classifier: Programming Language :: Python :: 3
Classifier: Programming Language :: Python :: 3.9
Classifier: Programming Language :: Python :: 3.10
Classifier: Programming Language :: Python :: 3.11
Requires-Dist: aiohttp (>=3.8.3,<4.0.0)
Requires-Dist: asyncselenium (>=0.0.2,<0.0.3)
Requires-Dist: dataclass-type-validator (>=0.1.2,<0.2.0)
Requires-Dist: dateutils (>=0.6.12,<0.7.0)
Requires-Dist: export (>=0.2.0,<0.3.0)
Requires-Dist: httpx (>=0.23.3,<0.24.0)
Requires-Dist: pytest-localserver (>=0.7.0,<0.8.0)
Requires-Dist: python-dotenv (>=0.21.1,<0.22.0)
Requires-Dist: rich (>=12.5.1,<13.0.0)
Requires-Dist: screeninfo (>=0.8.1,<0.9.0)
Requires-Dist: selenium (>=4.4.3,<5.0.0)
Requires-Dist: self (>=2020.12.3,<2021.0.0)
Requires-Dist: termcolor (>=2.2.0,<3.0.0)
Requires-Dist: textual (>=0.6.0,<0.7.0)
Requires-Dist: typeguard (>=2.13.3,<3.0.0)
Requires-Dist: typer (>=0.6.1,<0.7.0)
Requires-Dist: valid8 (>=5.1.2,<6.0.0)
Requires-Dist: webdriver-manager (>=3.8.3,<4.0.0)
Requires-Dist: xdotool (>=0.4.0,<0.5.0) ; python_version >= "3.10" and python_version < "4.0"
